youtube_downloader/__init__.py
youtube_downloader/youtube_downloader.py
youtube_downloader2-0.0.3.dist-info/METADATA
youtube_downloader2-0.0.3.dist-info/WHEEL
youtube_downloader2-0.0.3.dist-info/top_level.txt
youtube_downloader2-0.0.3.dist-info/RECORD
